celery_dyrygent/__init__.py
celery_dyrygent/celery/__init__.py
celery_dyrygent/celery/entities.py
celery_dyrygent/celery/inspect.py
celery_dyrygent/tasks/__init__.py
celery_dyrygent/tasks/processor.py
celery_dyrygent/workflows/__init__.py
celery_dyrygent/workflows/exceptions.py
celery_dyrygent/workflows/node.py
celery_dyrygent/workflows/workflow.py
celery_dyrygent-0.8.0.dist-info/LICENSE.txt
celery_dyrygent-0.8.0.dist-info/METADATA
celery_dyrygent-0.8.0.dist-info/WHEEL
celery_dyrygent-0.8.0.dist-info/top_level.txt
celery_dyrygent-0.8.0.dist-info/RECORD
