Metadata-Version: 2.1
Name: celery-dyrygent
Version: 0.8.0
Summary: Celery extension for workflows processing
Home-page: https://github.com/ovh/celery-dyrygent
Author: OVH SAS
Author-email: opensource@ovh.net
License: UNKNOWN
Project-URL: Bug Reports, https://github.com/ovh/celery-dyrygent/issues
Project-URL: Source, https://github.com/ovh/celery-dyrygent
Platform: UNKNOWN
Classifier: Development Status :: 5 - Production/Stable
Classifier: Intended Audience :: Developers
Classifier: Topic :: Software Development
Classifier: License :: OSI Approved :: BSD License
Classifier: Programming Language :: Python :: 2
Classifier: Programming Language :: Python :: 2.7
Classifier: Programming Language :: Python :: 3
Classifier: Programming Language :: Python :: 3.6
Classifier: Programming Language :: Python :: 3.8
License-File: LICENSE.txt
Requires-Dist: celery (!=4.0.*,!=4.1.*,>=3.1.25)
